drf_fb_auth/__init__.py
drf_fb_auth-0.1.0.dist-info/WHEEL
drf_fb_auth-0.1.0.dist-info/METADATA
drf_fb_auth-0.1.0.dist-info/RECORD
