Metadata-Version: 2.1
Name: drf-fb-auth
Version: 0.1.0
Summary: Firebase Authentication for Django Rest Framework
Author: Ron Heimann
Author-email: ron.heimann@gmail.com
Requires-Python: >=3.8,<4.0
Classifier: Programming Language :: Python :: 3
Classifier: Programming Language :: Python :: 3.8
Classifier: Programming Language :: Python :: 3.9
